pynmodl/__init__.py
pynmodl/lems.py
pynmodl/lems_helpers.py
pynmodl/model_utils.py
pynmodl/nmodl.py
pynmodl/unparser.py
pynmodl/grammar/assigned.tx
pynmodl/grammar/breakpoint.tx
pynmodl/grammar/comment.tx
pynmodl/grammar/constant.tx
pynmodl/grammar/derivative.tx
pynmodl/grammar/expressions.tx
pynmodl/grammar/include.tx
pynmodl/grammar/independent.tx
pynmodl/grammar/initial.tx
pynmodl/grammar/keyword.tx
pynmodl/grammar/kinetic.tx
pynmodl/grammar/local.tx
pynmodl/grammar/net_receive.tx
pynmodl/grammar/neuron.tx
pynmodl/grammar/nmodl.tx
pynmodl/grammar/parameter.tx
pynmodl/grammar/solvable_block.tx
pynmodl/grammar/solve.tx
pynmodl/grammar/state.tx
pynmodl/grammar/table.tx
pynmodl/grammar/title.tx
pynmodl/grammar/units.tx
pynmodl/grammar/variable.tx
pynmodl/grammar/verbatim.tx
pynmodl/tests/parsing/icg-K-semanticErrors.dat
pynmodl/tests/sample_mods/123815_Kaxon.mod
pynmodl/tests/sample_mods/kd.mod
pynmodl/tests/sample_mods/na.mod
pynmodlt-0.1.2.dist-info/LICENSE
pynmodlt-0.1.2.dist-info/METADATA
pynmodlt-0.1.2.dist-info/WHEEL
pynmodlt-0.1.2.dist-info/top_level.txt
pynmodlt-0.1.2.dist-info/RECORD
